ScriptsSignal/__init__.py
ScriptsSignal/signal.py
scriptsignals-0.1.7.dist-info/licenses/LICENSE
scriptsignals-0.1.7.dist-info/METADATA
scriptsignals-0.1.7.dist-info/WHEEL
scriptsignals-0.1.7.dist-info/top_level.txt
scriptsignals-0.1.7.dist-info/RECORD
