Metadata-Version: 2.4
Name: ScriptSignals
Version: 0.1.7
Summary: esta libreria te permitira comunicar varios scripts de python
Home-page: https://github.com/facu-programer/PySignal
Author: Facundo Efimenco
Author-email: facu22251@gmail.com
Classifier: Programming Language :: Python :: 3
Requires-Python: >=3.6
License-File: LICENSE
Dynamic: author
Dynamic: author-email
Dynamic: classifier
Dynamic: description
Dynamic: description-content-type
Dynamic: home-page
Dynamic: license-file
Dynamic: requires-python
Dynamic: summary
